MANIFEST.in
README.rst
setup.cfg
setup.py
ccs811_exporter/__about__.py
ccs811_exporter/__init__.py
ccs811_exporter/__main__.py
ccs811_exporter/exporter.py
ccs811_exporter.egg-info/PKG-INFO
ccs811_exporter.egg-info/SOURCES.txt
ccs811_exporter.egg-info/dependency_links.txt
ccs811_exporter.egg-info/entry_points.txt
ccs811_exporter.egg-info/requires.txt
ccs811_exporter.egg-info/top_level.txt