Metadata-Version: 1.1
Name: ccs811-exporter
Version: 0.1.0
Summary: Prometheus exporter for the ams CCS811 sensor
Home-page: https://github.com/ashtreefarms/ccs811_exporter
Author: Jake Krog
Author-email: jake.krog@gmail.com
License: MIT
Keywords: raspberry pi,rpi,prometheus,CCS811,i2c,temperature,eco2,tvoc
Platform: UNKNOWN
Classifier: Development Status :: 4 - Beta
Classifier: Environment :: Console
Classifier: Intended Audience :: Education
Classifier: Intended Audience :: Developers
Classifier: License :: OSI Approved :: MIT License
Classifier: Programming Language :: Python :: 3
Classifier: Topic :: System :: Monitoring
